robotclean/__init__.py
robotclean/__main__.py
robotclean/__version__.py
robotclean/code_formatters.py
robotframework_clean-1.2.1.dist-info/METADATA
robotframework_clean-1.2.1.dist-info/WHEEL
robotframework_clean-1.2.1.dist-info/entry_points.txt
robotframework_clean-1.2.1.dist-info/top_level.txt
robotframework_clean-1.2.1.dist-info/RECORD
