Metadata-Version: 2.1
Name: robotframework-clean
Version: 1.2.1
Summary: Utility scripts for formatting Robot Framework code
Home-page: https://github.com/bhisz/robotframework-maid
Author: Bartlomiej Hirsz
Author-email: bartek.hirsz@gmail.com
License: Apache License 2.0
Platform: any
Classifier: License :: OSI Approved :: Apache Software License
Classifier: Operating System :: OS Independent
Classifier: Programming Language :: Python :: 3.6
Classifier: Programming Language :: Python :: 3.7
Classifier: Programming Language :: Python :: 3.8
Classifier: Framework :: Robot Framework :: Tool
Classifier: Topic :: Software Development :: Quality Assurance
Classifier: Topic :: Utilities
Requires-Dist: robotframework (>=3.2.1)
